QuickPotato/__init__.py
QuickPotato/configuration/__init__.py
QuickPotato/configuration/management.py
QuickPotato/configuration/settings.py
QuickPotato/database/__init__.py
QuickPotato/database/operations.py
QuickPotato/database/queries.py
QuickPotato/database/schemas.py
QuickPotato/harness/__init__.py
QuickPotato/harness/measurements.py
QuickPotato/harness/results.py
QuickPotato/harness/testing.py
QuickPotato/profiling/__init__.py
QuickPotato/profiling/instrumentation.py
QuickPotato/profiling/interpreters.py
QuickPotato/profiling/intrusive.py
QuickPotato/statistical/__init__.py
QuickPotato/statistical/data.py
QuickPotato/statistical/hypothesis_tests.py
QuickPotato/statistical/verification.py
QuickPotato/statistical/visualizations.py
QuickPotato/utilities/__init__.py
QuickPotato/utilities/decorators.py
QuickPotato/utilities/defaults.py
QuickPotato/utilities/exceptions.py
QuickPotato/utilities/html_templates.py
QuickPotato-1.0.1.dist-info/LICENSE.md
QuickPotato-1.0.1.dist-info/METADATA
QuickPotato-1.0.1.dist-info/WHEEL
QuickPotato-1.0.1.dist-info/top_level.txt
QuickPotato-1.0.1.dist-info/RECORD
